oam/__init__.py
oam/manager.py
odoo_addon_manager-0.1.1.dist-info/LICENCE.md
odoo_addon_manager-0.1.1.dist-info/METADATA
odoo_addon_manager-0.1.1.dist-info/WHEEL
odoo_addon_manager-0.1.1.dist-info/entry_points.txt
odoo_addon_manager-0.1.1.dist-info/top_level.txt
odoo_addon_manager-0.1.1.dist-info/RECORD
