Metadata-Version: 2.1
Name: odoo-addon-manager
Version: 0.1.1
Summary: A tool to install and update odoo addons
Home-page: https://gitlab.com/e-cosi/odoo/oam
Author: e-COSI
Author-email: tech.odoo@e-cosi.com
License: UNKNOWN
Keywords: odoo,module,addon
Platform: UNKNOWN
Classifier: Development Status :: 3 - Alpha
Classifier: Environment :: Console
Classifier: Intended Audience :: Developers
Classifier: Topic :: Software Development
Classifier: Programming Language :: Python :: 3.6
Classifier: License :: OSI Approved :: GNU Affero General Public License v3 or later (AGPLv3+)
Requires-Dist: Click (>=7.0)
Requires-Dist: callable-pip (>=1.0.0)
Requires-Dist: fs (>=2.4.4)
Requires-Dist: packaging (>=19.0)
Requires-Dist: PyYAML (>=5.1)
Requires-Dist: pygit2 (>=0.27.4)
